Workbook

Sheet Raw_Data
A1: Month | B1: Department | C1: Revenue Budget | D1: Revenue Actual | E1: Expense Budget | F1: Expense Actual | G1: Headcount
A2: Jan | B2: Sales | C2: 500000 | D2: 525000 | E2: 120000 | F2: 118000 | G2: 25
A3: Jan | B3: Marketing | C3: 100000 | D3: 95000 | E3: 80000 | F3: 92000 | G3: 12
A4: Jan | B4: Operations | C4: 150000 | D4: 155000 | E4: 180000 | F4: 175000 | G4: 30
A5: Jan | B5: HR | C5: 0 | D5: 0 | E5: 60000 | F5: 62000 | G5: 8
A6: Feb | B6: IT | C6: 0 | D6: 0 | E6: 70000 | F6: 68000 | G6: 10
A7: Feb | B7: Sales | C7: 520000 | D7: 535000 | E7: 122000 | F7: 125000 | G7: 25
A8: Feb | B8: Marketing | C8: 105000 | D8: 110000 | E8: 82000 | F8: 85000 | G8: 12
A9: Feb | B9: Operations | C9: 155000 | D9: 160000 | E9: 182000 | F9: 190000 | G9: 30
A10: Feb | B10: HR | C10: 0 | D10: 0 | E10: 61000 | F10: 60000 | G10: 8
A11: Mar | B11: IT | C11: 0 | D11: 0 | E11: 72000 | F11: 75000 | G11: 10
A12: Mar | B12: Sales | C12: 540000 | D12: 565000 | E12: 125000 | F12: 127000 | G12: 26
A13: Mar | B13: Marketing | C13: 110000 | D13: 118000 | E13: 85000 | F13: 88000 | G13: 12
... A60: Dec | B60: HR | C60: 0 | D60: 0 | E60: 72000 | F60: 74000 | G60: 10
B61: IT | C61: 0 | D61: 0 | E61: 85000 | F61: 83000 | G61: 13

Sheet FP&A analysis
A1: FP&A analysis
A3: Month | B3: Revenue Budget | C3: Revenue Actual | D3: Revenue Var % | E3: Expense Budget | F3: Expense Actual | G3: Operating Profit
A4: Jan | B4: =SUM(Raw_Data!C2,Raw_Data!C3,Table1[[#This Row],[Revenue Budget]]) -> 750000 | C4: =SUM(Raw_Data!D2,Raw_Data!D3,Table1[[#This Row],[Revenue Actual ]]) -> 775000 | D4: =(C4-B4)/B4 -> 0.033333333 | E4: =SUM(Raw_Data!E2,Raw_Data!E3,Table1[[#This Row],[Expense Budget]],Raw_Data!E5) -> 440000 | F4: =SUM(Raw_Data!F2,Raw_Data!F3,Table1[[#This Row],[Expense Actual]],Raw_Data!F5) -> 447000 | G4: =C4-F4 -> 328000
A5: Feb | B5: =SUM(Raw_Data!C7,Raw_Data!C8,Raw_Data!C9) -> 780000 | C5: =SUM(Raw_Data!D7,Raw_Data!D9,Raw_Data!D8) -> 805000 | D5: =(C5-B5)/B5 -> 0.032051282 | E5: =SUM(Raw_Data!E6,Raw_Data!E7,Raw_Data!E8,Raw_Data!E9,Raw_Data!E10) -> 517000 | F5: =SUM(Raw_Data!F6,Raw_Data!F7,Raw_Data!F8,Raw_Data!F9,Raw_Data!F10) -> 528000 | G5: =C5-F5 -> 277000
A6: Mar | B6: =SUM(Raw_Data!C12,Raw_Data!C13,Raw_Data!C14,) -> 810000 | C6: =SUM(Raw_Data!D12,Raw_Data!D13,Raw_Data!D14) -> 841000 | D6: =(C6-B6)/B6 -> 0.038271605 | E6: =SUM(Raw_Data!E11,Raw_Data!E12,Raw_Data!E13,Raw_Data!E14,Raw_Data!E15) -> 529000 | F6: =SUM(Raw_Data!F11,Raw_Data!F12,Raw_Data!F13,Raw_Data!F14,Raw_Data!F15) -> 543000 | G6: =C6-F6 -> 298000
A7: Apr | B7: =SUM(Raw_Data!C17,Raw_Data!C18,Raw_Data!C19) -> 840000 | C7: =SUM(Raw_Data!D17,Raw_Data!D18,Raw_Data!D19) -> 857000 | D7: =(C7-B7)/B7 -> 0.020238095 | E7: =SUM(Raw_Data!E16,Raw_Data!E17,Raw_Data!E18,Raw_Data!E19,Raw_Data!E20) -> 539000 | F7: =SUM(Raw_Data!F16,Raw_Data!F17,Raw_Data!F18,Raw_Data!F19,Raw_Data!F20) -> 537000 | G7: =C7-F7 -> 320000
A8: May | B8: =SUM(Raw_Data!C22,Raw_Data!C23,Raw_Data!C24,) -> 865000 | C8: =SUM(Raw_Data!D22,Raw_Data!D23,Raw_Data!D24) -> 883000 | D8: =(C8-B8)/B8 -> 0.020809249 | E8: =SUM(Raw_Data!E21,Raw_Data!E22,Raw_Data!E23,Raw_Data!E24,Raw_Data!E25) -> 547000 | F8: =SUM(Raw_Data!F21,Raw_Data!F22,Raw_Data!F23,Raw_Data!F24,Raw_Data!E25) -> 552000 | G8: =C8-F8 -> 331000
A9: Jun | B9: =SUM(Raw_Data!C27,Raw_Data!C28,Raw_Data!C29) -> 890000 | C9: =SUM(Raw_Data!D27,Raw_Data!D28,Raw_Data!D29) -> 913000 | D9: =(C9-B9)/B9 -> 0.025842697 | E9: =SUM(Raw_Data!E26,Raw_Data!E27,Raw_Data!E29,Raw_Data!E30,Raw_Data!E28) -> 556000 | F9: =SUM(Raw_Data!F26,Raw_Data!F27,Raw_Data!F28,Raw_Data!F29,Raw_Data!F30) -> 559000 | G9: =C9-F9 -> 354000
A10: Jul | B10: =SUM(Raw_Data!C32,Raw_Data!C33,Raw_Data!C34) -> 915000 | C10: =SUM(Raw_Data!D32,Raw_Data!D33,Raw_Data!D34) -> 910000 | D10: =(C10-B10)/B10 -> -0.0054644809 | E10: =SUM(Raw_Data!E31,Raw_Data!E32,Raw_Data!E33,Raw_Data!E34,Raw_Data!E35) -> 566000 | F10: =SUM(Raw_Data!F31,Raw_Data!F32,Raw_Data!F33,Raw_Data!F34,Raw_Data!F35) -> 569000 | G10: =C10-F10 -> 341000
A11: Aug | B11: =SUM(Raw_Data!C38,Raw_Data!C39,Raw_Data!C37) -> 940000 | C11: =SUM(Raw_Data!D37,Raw_Data!D38,Raw_Data!D39) -> 962000 | D11: =(C11-B11)/B11 -> 0.023404255 | E11: =SUM(Raw_Data!E36,Raw_Data!E37,Raw_Data!E38,Raw_Data!E39,Raw_Data!E40) -> 577000 | F11: =SUM(Raw_Data!F36,Raw_Data!F37,Raw_Data!F38,Raw_Data!F39,Raw_Data!F40) -> 577000 | G11: =C11-F11 -> 385000
A12: Sep | B12: =SUM(Raw_Data!C42,Raw_Data!C43,Raw_Data!C44) -> 965000 | C12: =SUM(Raw_Data!D42,Raw_Data!D43,Raw_Data!D44) -> 981000 | D12: =(C12-B12)/B12 -> 0.016580311 | E12: =SUM(Raw_Data!E41,Raw_Data!E43,Raw_Data!E44,Raw_Data!E45,Raw_Data!E42) -> 586000 | F12: =SUM(Raw_Data!F41,Raw_Data!F42,Raw_Data!F43,Raw_Data!F44,Raw_Data!F45) -> 587000 | G12: =C12-F12 -> 394000
A13: Oct | B13: =SUM(Raw_Data!C47,Raw_Data!C48,Raw_Data!C49) -> 990000 | C13: =SUM(Raw_Data!D47,Raw_Data!D48,Raw_Data!D49) -> 1018000 | D13: =(C13-B13)/B13 -> 0.028282828 | E13: =SUM(Raw_Data!E46,Raw_Data!E47,Raw_Data!E48,Raw_Data!E50,Raw_Data!E49) -> 596000 | F13: =SUM(Raw_Data!F46,Raw_Data!F47,Raw_Data!F48,Raw_Data!F49,Raw_Data!F50) -> 596000 | G13: =C13-F13 -> 422000
A14: Nov | B14: =SUM(Raw_Data!C52,Raw_Data!C53,Raw_Data!C54) -> 1020000 | C14: =SUM(Raw_Data!D52,Raw_Data!D53,Raw_Data!D54) -> 1016000 | D14: =(C14-B14)/B14 -> -0.0039215686 | E14: =SUM(Raw_Data!E51,Raw_Data!E52,Raw_Data!E53,Raw_Data!E54,Raw_Data!E55) -> 607000 | F14: =SUM(Raw_Data!F51,Raw_Data!F52,Raw_Data!F53,Raw_Data!F54,Raw_Data!F55) -> 609000 | G14: =C14-F14 -> 407000
A15: Dec | B15: =SUM(Raw_Data!C57,Raw_Data!C58,Raw_Data!C59) -> 1050000 | C15: =SUM(Raw_Data!D57,Raw_Data!D58,Raw_Data!D59) -> 1092000 | D15: =(C15-B15)/B15 -> 0.04 | E15: =SUM(Raw_Data!E56,Raw_Data!E57,Raw_Data!E58,Raw_Data!E59,Raw_Data!E60) -> 621000 | F15: =SUM(Raw_Data!F56,Raw_Data!F57,Raw_Data!F58,Raw_Data!F59,Raw_Data!F60) -> 621000 | G15: =C15-F15 -> 471000
A18: OVERALL FP&A METRICS
A20: Metric | B20: Budget | C20: Actual | D20: Variance | E20: Variance%
A21: Revenue | B21: =SUM(B4:B16) -> 10815000 | C21: =SUM(C4:C15) -> 11053000 | D21: =C21-B21 -> 238000 | E21: =D21/B21 -> 0.022006472
A22: Expenses | B22: =SUM(E4:E15) -> 6681000 | C22: =SUM(F4:F15) -> 6725000 | D22: =C22-B22 -> 44000 | E22: =D22/B22 -> 0.0065858404
A23: Operating Profit | B23: =B21-B22 -> 4134000 | C23: =C21-C22 -> 4328000 | D23: =C23-B23 -> 194000 | E23: =D23/B23 -> 0.046927915
A25: VARIANCE INVESTIGATION SECTION
A27: Month | B27: Expense Var ₹ | C27: Expensne Var% | D27: Profit Var ₹ | E27: Profit Var %
A28: Jan | B28: =F4-E4 -> 7000 | C28: =B28/E4 -> 0.015909091 | D28: =G4-(B4-E4) -> 18000 | E28: =D28/(B4-E4) -> 0.058064516
A29: Feb | B29: =F5-E5 -> 11000 | C29: =B29/E5 -> 0.021276596 | D29: =G5-(B5-E5) -> 14000 | E29: =D29/(B5-E5) -> 0.053231939
A30: Mar | B30: =F6-E6 -> 14000 | C30: =B30/E6 -> 0.026465028 | D30: =G6-(B6-E6) -> 17000 | E30: =D30/(B6-E6) -> 0.060498221
A31: Apr | B31: =F7-E7 -> -2000 | C31: =B31/E7 -> -0.0037105751 | D31: =G7-(B7-E7) -> 19000 | E31: =D31/(B7-E7) -> 0.063122924
A32: May | B32: =F8-E8 -> 5000 | C32: =B32/E8 -> 0.0091407678 | D32: =G8-(B8-E8) -> 13000 | E32: =D32/(B8-E8) -> 0.040880503
A33: Jun | B33: =F9-E9 -> 3000 | C33: =B33/E9 -> 0.0053956835 | D33: =G9-(B9-E9) -> 20000 | E33: =D33/(B9-E9) -> 0.05988024
A34: Jul | B34: =F10-E10 -> 3000 | C34: =B34/E10 -> 0.0053003534 | D34: =G10-(B10-E10) -> -8000 | E34: =D34/(B10-E10) -> -0.022922636
A35: Aug | B35: =F11-E11 -> 0 | C35: =B35/E11 -> 0 | D35: =G11-(B11-E11) -> 22000 | E35: =D35/(B11-E11) -> 0.060606061
A36: Sep | B36: =F12-E12 -> 1000 | C36: =B36/E12 -> 0.0017064846 | D36: =G12-(B12-E12) -> 15000 | E36: =D36/(B12-E12) -> 0.039577836
A37: Oct | B37: =F13-E13 -> 0 | C37: =B37/E13 -> 0 | D37: =G13-(B13-E13) -> 28000 | E37: =D37/(B13-E13) -> 0.07106599
A38: Nov | B38: =F14-E14 -> 2000 | C38: =B38/E14 -> 0.0032948929 | D38: =G14-(B14-E14) -> -6000 | E38: =D38/(B14-E14) -> -0.014527845
A39: Dec | B39: =F15-E15 -> 0 | C39: =B39/E15 -> 0 | D39: =G15-(B15-E15) -> 42000 | E39: =D39/(B15-E15) -> 0.097902098

Sheet Dashboard
B1: ACTUAL REVENUE YTD
A4: Month | B4: Revenue Budget | C4: Revenue Actual
A5: Jan | B5: ='FP&A analysis'!B4 -> 750000 | C5: ='FP&A analysis'!C4 -> 775000
A6: Feb | B6: ='FP&A analysis'!B5 -> 780000 | C6: ='FP&A analysis'!C5 -> 805000
A7: Mar | B7: ='FP&A analysis'!B6 -> 810000 | C7: ='FP&A analysis'!C6 -> 841000
A8: Apr | B8: ='FP&A analysis'!B7 -> 840000 | C8: ='FP&A analysis'!C7 -> 857000
A9: May | B9: ='FP&A analysis'!B8 -> 865000 | C9: ='FP&A analysis'!C8 -> 883000
A10: Jun | B10: ='FP&A analysis'!B9 -> 890000 | C10: ='FP&A analysis'!C9 -> 913000
A11: Jul | B11: ='FP&A analysis'!B10 -> 915000 | C11: ='FP&A analysis'!C10 -> 910000
A12: Aug | B12: ='FP&A analysis'!B11 -> 940000 | C12: ='FP&A analysis'!C11 -> 962000
A13: Sep | B13: ='FP&A analysis'!B12 -> 965000 | C13: ='FP&A analysis'!C12 -> 981000
A14: Oct | B14: ='FP&A analysis'!B13 -> 990000 | C14: ='FP&A analysis'!C13 -> 1018000
A15: Nov | B15: ='FP&A analysis'!B14 -> 1020000 | C15: ='FP&A analysis'!C14 -> 1016000
A16: Dec | B16: ='FP&A analysis'!B15 -> 1050000 | C16: ='FP&A analysis'!C15 -> 1092000
B19: ACTUAL EXPENSE YTD
A20: Month | B20: Expense Budget | C20: Expense Actual
A21: Jan | B21: ='FP&A analysis'!E4 -> 440000 | C21: ='FP&A analysis'!F4 -> 447000
A22: Feb | B22: ='FP&A analysis'!E5 -> 517000 | C22: ='FP&A analysis'!F5 -> 528000
A23: Mar | B23: ='FP&A analysis'!E6 -> 529000 | C23: ='FP&A analysis'!F6 -> 543000
A24: Apr | B24: ='FP&A analysis'!E7 -> 539000 | C24: ='FP&A analysis'!F7 -> 537000
A25: May | B25: ='FP&A analysis'!E8 -> 547000 | C25: ='FP&A analysis'!F8 -> 552000
A26: Jun | B26: ='FP&A analysis'!E9 -> 556000 | C26: ='FP&A analysis'!F9 -> 559000
A27: Jul | B27: ='FP&A analysis'!E10 -> 566000 | C27: ='FP&A analysis'!F10 -> 569000
A28: Aug | B28: ='FP&A analysis'!E11 -> 577000 | C28: ='FP&A analysis'!F11 -> 577000
A29: Sept | B29: ='FP&A analysis'!E12 -> 586000 | C29: ='FP&A analysis'!F12 -> 587000
A30: Oct | B30: ='FP&A analysis'!E13 -> 596000 | C30: ='FP&A analysis'!F13 -> 596000
A31: Nov | B31: ='FP&A analysis'!E14 -> 607000 | C31: ='FP&A analysis'!F14 -> 609000
A32: Dec | B32: ='FP&A analysis'!E15 -> 621000 | C32: ='FP&A analysis'!F15 -> 621000
A34: Management Insights on both Actual revenue YTD & Actual Expense YTD
A36: 1. Revenue Performance:
A37: Actual revenue is ahead of budget overall, indicating positive revenue performance.
A39: 2. Expense monitoring:
A40: Actual expensesshould be monitored against the cumulative budget to identify months where spending is accelerating.
A42: 3. Profitability:
A43: Operating profit provides a combined view of revenue and expense performance and highlights whether revenue growth is translating into profitability.
A45: 4. Variance Focus:
A46: Months with negative revenue variance require management attention to understand the underlying business drivers.
A48: 5. YTD perspective:
A49: YTD revenue and expense allow management to assess cumulative performance rather than relying on individual monthly fluctuations .
